langchain_spicedb/__init__.py
langchain_spicedb/core.py
langchain_spicedb/langchain_runnable.py
langchain_spicedb/langgraph_node.py
langchain_spicedb/retrievers.py
langchain_spicedb/tools.py
langchain_spicedb-0.1.1.dist-info/licenses/LICENSE
langchain_spicedb-0.1.1.dist-info/METADATA
langchain_spicedb-0.1.1.dist-info/WHEEL
langchain_spicedb-0.1.1.dist-info/top_level.txt
langchain_spicedb-0.1.1.dist-info/RECORD
