Metadata-Version: 2.4
Name: langchain-spicedb
Version: 0.1.1
Summary: SpiceDB authorization for LangChain RAG pipelines and agents - fine-grained access control for AI applications
Author-email: Sohan Maheshwar <sohan.maheshwar@authzed.com>
License-Expression: Apache-2.0
Project-URL: Homepage, https://github.com/authzed/langchain-spicedb
Project-URL: Documentation, https://github.com/authzed/langchain-spicedb/blob/main/README.md
Project-URL: Repository, https://github.com/authzed/langchain-spicedb
Project-URL: Issues, https://github.com/authzed/langchain-spicedb/issues
Keywords: langchain,spicedb,authorization,rag,ai,llm,permissions,langgraph
Classifier: Development Status :: 4 - Beta
Classifier: Intended Audience :: Developers
Classifier: Programming Language :: Python :: 3
Classifier: Programming Language :: Python :: 3.9
Classifier: Programming Language :: Python :: 3.10
Classifier: Programming Language :: Python :: 3.11
Classifier: Programming Language :: Python :: 3.12
Classifier: Topic :: Software Development :: Libraries :: Python Modules
Classifier: Topic :: Security
Requires-Python: >=3.9
License-File: LICENSE
Requires-Dist: authzed>=0.7.0
Requires-Dist: grpcio>=1.50.0
Requires-Dist: grpcio-tools>=1.50.0
Provides-Extra: langchain
Requires-Dist: langchain-core>=0.1.0; extra == "langchain"
Provides-Extra: langgraph
Requires-Dist: langgraph>=0.0.20; extra == "langgraph"
Provides-Extra: all
Requires-Dist: langchain-core>=0.1.0; extra == "all"
Requires-Dist: langgraph>=0.0.20; extra == "all"
Provides-Extra: dev
Requires-Dist: pytest>=7.0.0; extra == "dev"
Requires-Dist: pytest-asyncio>=0.21.0; extra == "dev"
Requires-Dist: pytest-mock>=3.12.0; extra == "dev"
Requires-Dist: python-dotenv>=1.0.0; extra == "dev"
Requires-Dist: langchain-openai>=0.0.5; extra == "dev"
Requires-Dist: langchain-tests>=0.3.0; extra == "dev"
Provides-Extra: test
Requires-Dist: pytest>=7.0.0; extra == "test"
Requires-Dist: pytest-asyncio>=0.21.0; extra == "test"
Requires-Dist: pytest-mock>=3.12.0; extra == "test"
Requires-Dist: langchain-tests>=0.3.0; extra == "test"
Dynamic: license-file
